<?xml version="1.0" encoding="UTF-8"?>
<beans xmlns="http://www.springframework.org/schema/beans"
	xmlns:xsi="http://www.w3.org/2001/XMLSchema-instance" xmlns:mvc="http://www.springframework.org/schema/mvc"
	xmlns:context="http://www.springframework.org/schema/context"
	xsi:schemaLocation="
		http://www.springframework.org/schema/beans http://www.springframework.org/schema/beans/spring-beans-3.1.xsd
		http://www.springframework.org/schema/mvc http://www.springframework.org/schema/mvc/spring-mvc-3.1.xsd
		http://www.springframework.org/schema/context http://www.springframework.org/schema/context/spring-context-3.1.xsd">

	<context:component-scan base-package="com.wavemaker.spinup.web" />

	<mvc:annotation-driven />

	<mvc:resources mapping="/resources/**" location="/resources/" />
	<mvc:resources mapping="/dijit/**" location="/dijit/" />
	<mvc:resources mapping="/dojo/**" location="/dojo/" />
	<mvc:resources mapping="/dojox/**" location="/dojox/" />
	<mvc:resources mapping="/resources/**" location="/resources/" />

	<bean
		class="org.springframework.web.servlet.view.InternalResourceViewResolver">
		<property name="prefix" value="/WEB-INF/views/" />
		<property name="suffix" value=".jsp" />
	</bean>

	<bean name="wavemakerMongoService" class="org.cloudfoundry.client.lib.CloudService">
		<property name="name" value="wavemaker"/>
		<property name="type" value="database"/>
		<property name="vendor" value="mongodb"/>
		<property name="version" value="1.8"/>
		<property name="tier" value="free"/>
	</bean>

	<bean name="spinupService" class="com.wavemaker.tools.cloudfoundry.spinup.DefaultSpinupService" autowire="byType">
		<property name="serviceNames">
			<list>
				<value>wavemaker</value>
			</list>
		</property>
		<property name="services">
			<list>
				<ref bean="wavemakerMongoService"/>
			</list>
		</property>
	</bean>

	<bean class="com.wavemaker.tools.cloudfoundry.spinup.authentication.SharedSecretPropagation" />


</beans>